nerval/__init__.py
nerval/cli.py
nerval/evaluate.py
nerval/parse.py
nerval/utils.py
teklia_nerval-0.3.3.dist-info/METADATA
teklia_nerval-0.3.3.dist-info/WHEEL
teklia_nerval-0.3.3.dist-info/entry_points.txt
teklia_nerval-0.3.3.dist-info/top_level.txt
teklia_nerval-0.3.3.dist-info/RECORD
