Metadata-Version: 2.1
Name: teklia-nerval
Version: 0.3.3
Summary: Tool to evaluate NER on noisy text.
Author-email: Teklia <contact@teklia.com>
Maintainer-email: Teklia <contact@teklia.com>
Keywords: python
Classifier: Programming Language :: Python :: 3 :: Only
Classifier: Programming Language :: Python :: 3.10
Classifier: Programming Language :: Python :: 3.11
Classifier: Programming Language :: Python :: 3.12
Requires-Python: >=3.10
Requires-Dist: editdistance==0.8.1
Requires-Dist: edlib==1.3.9.post1
Requires-Dist: prettytable==3.9.0
